cala/__init__.py
cala-0.1.0.dist-info/METADATA
cala-0.1.0.dist-info/WHEEL
cala-0.1.0.dist-info/RECORD
